deepwto/__init__.py
deepwto/article_upload.py
deepwto/cited_upload.py
deepwto/constants.py
deepwto/explore.py
deepwto/factual_upload.py
deepwto/graphql.py
deepwto/read_json.py
deepwto-0.1.1.dist-info/LICENSE
deepwto-0.1.1.dist-info/METADATA
deepwto-0.1.1.dist-info/WHEEL
deepwto-0.1.1.dist-info/top_level.txt
deepwto-0.1.1.dist-info/RECORD
