Metadata-Version: 2.1
Name: deepwto
Version: 0.1.1
Summary: DeepWTO Database API
Home-page: https://github.com/DeepWTO/deepwto-api
Author: zcryoon
Author-email: syyun@snu.ac.kr
License: UNKNOWN
Platform: UNKNOWN
Classifier: Programming Language :: Python :: 3
Classifier: License :: OSI Approved :: MIT License
Classifier: Operating System :: OS Independent
Requires-Python: >=3.6
Requires-Dist: requests
